estela_cli/__init__.py
estela_cli/__main__.py
estela_cli/context.py
estela_cli/deploy.py
estela_cli/estela_client.py
estela_cli/init.py
estela_cli/login.py
estela_cli/logout.py
estela_cli/templates.py
estela_cli/utils.py
estela_cli/create/__init__.py
estela_cli/create/cronjob.py
estela_cli/create/job.py
estela_cli/create/project.py
estela_cli/data/__init__.py
estela_cli/data/job.py
estela_cli/delete/__init__.py
estela_cli/delete/project.py
estela_cli/list/__init__.py
estela_cli/list/cronjob.py
estela_cli/list/job.py
estela_cli/list/project.py
estela_cli/list/spider.py
estela_cli/stop/__init__.py
estela_cli/stop/job.py
estela_cli/update/__init__.py
estela_cli/update/cronjob.py
estela_cli/update/job.py
estela-0.2.7.dist-info/METADATA
estela-0.2.7.dist-info/WHEEL
estela-0.2.7.dist-info/entry_points.txt
estela-0.2.7.dist-info/top_level.txt
estela-0.2.7.dist-info/RECORD
