Metadata-Version: 2.1
Name: estela
Version: 0.2.7
Summary: Estela Command Line Interface
Home-page: UNKNOWN
License: UNKNOWN
Platform: UNKNOWN
Classifier: Development Status :: 3 - Alpha
Classifier: Operating System :: OS Independent
Classifier: Programming Language :: Python :: 3
Classifier: Topic :: Utilities
Requires-Dist: click
Requires-Dist: docker
Requires-Dist: pyyaml
Requires-Dist: requests
Requires-Dist: requests-toolbelt
Requires-Dist: tabulate
Requires-Dist: tqdm
